mock_vws/__init__.py
mock_vws/_base64_decoding.py
mock_vws/_constants.py
mock_vws/_database_matchers.py
mock_vws/_mock_common.py
mock_vws/_query_tools.py
mock_vws/database.py
mock_vws/image_matchers.py
mock_vws/py.typed
mock_vws/states.py
mock_vws/target.py
mock_vws/target_manager.py
mock_vws/target_raters.py
mock_vws/_flask_server/Dockerfile
mock_vws/_flask_server/__init__.py
mock_vws/_flask_server/healthcheck.py
mock_vws/_flask_server/target_manager.py
mock_vws/_flask_server/vwq.py
mock_vws/_flask_server/vws.py
mock_vws/_query_validators/__init__.py
mock_vws/_query_validators/accept_header_validators.py
mock_vws/_query_validators/auth_validators.py
mock_vws/_query_validators/content_length_validators.py
mock_vws/_query_validators/content_type_validators.py
mock_vws/_query_validators/date_validators.py
mock_vws/_query_validators/exceptions.py
mock_vws/_query_validators/fields_validators.py
mock_vws/_query_validators/image_validators.py
mock_vws/_query_validators/include_target_data_validators.py
mock_vws/_query_validators/num_results_validators.py
mock_vws/_query_validators/project_state_validators.py
mock_vws/_requests_mock_server/__init__.py
mock_vws/_requests_mock_server/decorators.py
mock_vws/_requests_mock_server/mock_web_query_api.py
mock_vws/_requests_mock_server/mock_web_services_api.py
mock_vws/_services_validators/__init__.py
mock_vws/_services_validators/active_flag_validators.py
mock_vws/_services_validators/auth_validators.py
mock_vws/_services_validators/content_length_validators.py
mock_vws/_services_validators/content_type_validators.py
mock_vws/_services_validators/date_validators.py
mock_vws/_services_validators/exceptions.py
mock_vws/_services_validators/image_validators.py
mock_vws/_services_validators/json_validators.py
mock_vws/_services_validators/key_validators.py
mock_vws/_services_validators/metadata_validators.py
mock_vws/_services_validators/name_validators.py
mock_vws/_services_validators/project_state_validators.py
vws_python_mock-2025.3.10.1.dist-info/LICENSE
vws_python_mock-2025.3.10.1.dist-info/METADATA
vws_python_mock-2025.3.10.1.dist-info/WHEEL
vws_python_mock-2025.3.10.1.dist-info/top_level.txt
vws_python_mock-2025.3.10.1.dist-info/RECORD
