Metadata-Version: 2.2
Name: vws-python-mock
Version: 2025.3.10.1
Summary: A mock for the Vuforia Web Services (VWS) API.
Author-email: Adam Dangoor <adamdangoor@gmail.com>
License: The MIT License
Project-URL: Documentation, https://vws-python.github.io/vws-python-mock/
Project-URL: Source, https://github.com/VWS-Python/vws-python-mock
Keywords: client,fake,mock,vuforia,vws
Classifier: Development Status :: 5 - Production/Stable
Classifier: Environment :: Web Environment
Classifier: Framework :: Pytest
Classifier: License :: OSI Approved :: MIT License
Classifier: Operating System :: Microsoft :: Windows
Classifier: Operating System :: POSIX
Classifier: Programming Language :: Python :: 3 :: Only
Classifier: Programming Language :: Python :: 3.13
Requires-Python: >=3.13
License-File: LICENSE
Requires-Dist: beartype>=0.19.0
Requires-Dist: flask>=3.0.3
Requires-Dist: numpy>=1.26.4
Requires-Dist: pillow>=11.0.0
Requires-Dist: piq>=0.8.0
Requires-Dist: pydantic-settings>=2.6.1
Requires-Dist: requests>=2.32.3
Requires-Dist: responses>=0.25.3
Requires-Dist: torch>=2.5.1
Requires-Dist: torchmetrics>=1.5.1
Requires-Dist: tzdata; sys_platform == "win32"
Requires-Dist: vws-auth-tools>=2024.7.12
Requires-Dist: werkzeug>=3.1.2
Provides-Extra: dev
Requires-Dist: actionlint-py==1.7.7.23; extra == "dev"
Requires-Dist: check-manifest==0.50; extra == "dev"
Requires-Dist: check-wheel-contents==0.6.1; extra == "dev"
Requires-Dist: deptry==0.23.0; extra == "dev"
Requires-Dist: dirty-equals==0.9.0; extra == "dev"
Requires-Dist: doc8==1.1.1; extra == "dev"
Requires-Dist: doccmd==2025.3.6; extra == "dev"
Requires-Dist: docformatter==1.7.5; extra == "dev"
Requires-Dist: docker==7.1.0; extra == "dev"
Requires-Dist: enum-tools[sphinx]==0.12.0; extra == "dev"
Requires-Dist: freezegun==1.5.1; extra == "dev"
Requires-Dist: furo==2024.8.6; extra == "dev"
Requires-Dist: interrogate==1.7.0; extra == "dev"
Requires-Dist: mypy[faster-cache]==1.15.0; extra == "dev"
Requires-Dist: mypy-strict-kwargs==2024.12.25; extra == "dev"
Requires-Dist: pre-commit==4.1.0; extra == "dev"
Requires-Dist: pydocstyle==6.3; extra == "dev"
Requires-Dist: pyenchant==3.3.0rc1; extra == "dev"
Requires-Dist: pylint==3.3.4; extra == "dev"
Requires-Dist: pylint-per-file-ignores==1.4.0; extra == "dev"
Requires-Dist: pyproject-fmt==2.5.1; extra == "dev"
Requires-Dist: pyright==1.1.396; extra == "dev"
Requires-Dist: pyroma==4.2; extra == "dev"
Requires-Dist: pytest==8.3.5; extra == "dev"
Requires-Dist: pytest-cov==6.0.0; extra == "dev"
Requires-Dist: pytest-retry==1.7.0; extra == "dev"
Requires-Dist: pytest-xdist==3.6.1; extra == "dev"
Requires-Dist: python-dotenv==1.0.1; extra == "dev"
Requires-Dist: pyyaml==6.0.2; extra == "dev"
Requires-Dist: requests-mock-flask==2025.1.13; extra == "dev"
Requires-Dist: ruff==0.9.10; extra == "dev"
Requires-Dist: shellcheck-py==0.10.0.1; extra == "dev"
Requires-Dist: shfmt-py==3.7.0.1; extra == "dev"
Requires-Dist: sphinx==8.2.3; extra == "dev"
Requires-Dist: sphinx-copybutton==0.5.2; extra == "dev"
Requires-Dist: sphinx-lint==1.0.0; extra == "dev"
Requires-Dist: sphinx-paramlinks==0.6; extra == "dev"
Requires-Dist: sphinx-pyproject==0.3.0; extra == "dev"
Requires-Dist: sphinx-substitution-extensions==2025.3.3; extra == "dev"
Requires-Dist: sphinx-toolbox==3.9.0; extra == "dev"
Requires-Dist: sphinxcontrib-httpdomain==1.8.1; extra == "dev"
Requires-Dist: sphinxcontrib-spelling==8.0.1; extra == "dev"
Requires-Dist: sybil==9.1.0; extra == "dev"
Requires-Dist: tenacity==9.0.0; extra == "dev"
Requires-Dist: types-docker==7.1.0.20241229; extra == "dev"
Requires-Dist: types-pyyaml==6.0.12.20241230; extra == "dev"
Requires-Dist: types-requests==2.32.0.20250306; extra == "dev"
Requires-Dist: urllib3==2.3.0; extra == "dev"
Requires-Dist: vulture==2.14; extra == "dev"
Requires-Dist: vws-python==2024.9.21; extra == "dev"
Requires-Dist: vws-test-fixtures==2023.3.5; extra == "dev"
Requires-Dist: vws-web-tools==2024.10.6.1; extra == "dev"
Requires-Dist: yamlfix==1.17.0; extra == "dev"
Provides-Extra: release
Requires-Dist: check-wheel-contents==0.6.1; extra == "release"
